{
"Items": [
	{
		"title": "doog flips",
		"requiredCoinz": 15,
		"coinzPerSecond": 0.1
	},

	{
		"title": "hog flips",
		"requiredCoinz": 100,
		"coinzPerSecond": 1
	},

	{
		"title": "bob does it",
		"requiredCoinz": 1100,
		"coinzPerSecond": 8
	},

	{
		"title": "little bobby",
		"requiredCoinz": 12000,
		"coinzPerSecond": 47
	},

	{
		"title": "building 5",
		"requiredCoinz": 130000,
		"coinzPerSecond": 260
	},
	
	{
		"title": "building 6",
		"requiredCoinz": 1400000,
		"coinzPerSecond": 1400
	},

	{
		"title": "building 7",
		"requiredCoinz": 20000000,
		"coinzPerSecond": 78000
	},

	{
		"title": "building 8",
		"requiredCoinz": 330000000,
		"coinzPerSecond": 44000
	},

	{
		"title": "building 9",
		"requiredCoinz": 5100000000,
		"coinzPerSecond": 260000
	},

	{
		"title": "doug flies away!!!! lol jk",
		"requiredCoinz": 75000000000,
		"coinzPerSecond": 1600000
	},

	{
		"title": "building 11",
		"requiredCoinz": 75000000000,
		"coinzPerSecond": 1600000
	},

	{
		"title": "building 12",
		"requiredCoinz": 75000000000,
		"coinzPerSecond": 1600000
	}
]
}